CHANGES
MANIFEST.in
README
ez_setup.py
mvtest.py
setup.cfg
setup.py
meanvar/__init__.py
meanvar/mv_esteq.py
meanvar/mvresult.py
meanvar/mvstandardizer.py
meanvar/simple_timer.py
mvtest.egg-info/PKG-INFO
mvtest.egg-info/SOURCES.txt
mvtest.egg-info/dependency_links.txt
mvtest.egg-info/requires.txt
mvtest.egg-info/top_level.txt
scripts/mvmany.py
tests/__init__.py
tests/test_analyze_bed.py
tests/test_analyze_mv2_tped.py
tests/test_analyze_ped.py
tests/test_analyze_tped.py
tests/test_cmdline.py
tests/test_cmdline_mach.py
tests/test_cmdline_pedcols.py
tests/test_cmdline_phenocovar.py
tests/test_pedigree_parser.py
tests/test_standardization.py
tests/test_transped_parser.py
tests/bedfiles/analysis.bed
tests/bedfiles/analysis.bim
tests/bedfiles/analysis.fam
tests/bedfiles/missing
tests/bedfiles/ped_missing.bed
tests/bedfiles/ped_missing.bim
tests/bedfiles/ped_missing.fam
tests/bedfiles/ped_nomiss.bed
tests/bedfiles/ped_nomiss.bim
tests/bedfiles/ped_nomiss.fam